docker_replay/__init__.py
docker_replay/args.py
docker_replay/models.py
docker_replay/opts.py
docker_replay/parser.py
docker_replay/version.py
docker_replay-1.5.dist-info/LICENSE
docker_replay-1.5.dist-info/METADATA
docker_replay-1.5.dist-info/WHEEL
docker_replay-1.5.dist-info/entry_points.txt
docker_replay-1.5.dist-info/top_level.txt
docker_replay-1.5.dist-info/RECORD
