Metadata-Version: 2.1
Name: docker-replay
Version: 1.5
Summary: Generate docker run commands from running containers
Home-page: https://github.com/bcicen/docker-replay
Author: Bradley Cicenas
Author-email: bradley.cicenas@gmail.com
License: http://opensource.org/licenses/MIT
Keywords: docker docker-py devops
Platform: UNKNOWN
Classifier: Intended Audience :: Developers
Classifier: License :: OSI Approved :: MIT License 
Classifier: Natural Language :: English
Classifier: Programming Language :: Python
Classifier: Programming Language :: Python :: 2.7
Classifier: Programming Language :: Python :: 3.4
Requires-Dist: docker (>=2.4.2)
